m3_xlrd/__init__.py
m3_xlrd/biffh.py
m3_xlrd/book.py
m3_xlrd/compdoc.py
m3_xlrd/formatting.py
m3_xlrd/formula.py
m3_xlrd/info.py
m3_xlrd/licences.py
m3_xlrd/sheet.py
m3_xlrd/timemachine.py
m3_xlrd/xldate.py
m3_xlrd/xlsx.py
m3_xlrd/doc/compdoc.html
m3_xlrd/doc/xlrd.html
m3_xlrd/examples/namesdemo.xls
m3_xlrd/examples/xlrdnameAPIdemo.py
m3_xlrd-0.9.4.2.dist-info/LICENSE
m3_xlrd-0.9.4.2.dist-info/METADATA
m3_xlrd-0.9.4.2.dist-info/WHEEL
m3_xlrd-0.9.4.2.dist-info/top_level.txt
m3_xlrd-0.9.4.2.dist-info/RECORD
